[
  {
    "id": 1,
    "name": "Lance Olenik",
    "email": "lance@oleniks.net",
    "phone": "2085046918",
    "address1": "2360 Santalema Dr.",
    "address2": "",
    "city": "Idaho Falls",
    "state": "ID",
    "zip": "83404",
    "guestOf": "Both",
    "createdAt": "2025-05-13T21:08:54.214Z",
    "updatedAt": "2025-05-13T21:38:20.564Z",
    "plusOne": "",
    "children": 0,
    "attending": "No",
    "dateTime": "2025-05-06T20:49:57.672Z"
  },
  {
    "id": 2,
    "name": "New Guy",
    "email": "lolenik@gmail.com",
    "phone": "9876543210",
    "address1": "123 Main St",
    "address2": "",
    "city": "Beverly Hills",
    "state": "CA",
    "zip": "90210",
    "guestOf": "Both",
    "plusOne": "Wife Guy",
    "children": 2,
    "attending": "Yes",
    "dateTime": "2025-05-07T23:11:59.955Z",
    "createdAt": "2025-05-13T22:16:25.533Z",
    "updatedAt": "2025-05-14T20:03:42.188Z"
  },
  {
    "id": 3,
    "name": "Test Dude",
    "email": "info@lokowebdesign.com",
    "phone": "1234567890",
    "address1": "5 Main St.",
    "address2": "",
    "city": "Place",
    "state": "ID",
    "zip": "83404",
    "guestOf": "Groom",
    "plusOne": "Wife Dude",
    "children": 1,
    "attending": "Yes",
    "dateTime": "2025-05-14T20:58:51.297Z",
    "createdAt": "2025-05-13T22:53:58.263Z",
    "updatedAt": "2025-05-14T20:58:51.297Z"
  },
  {
    "id": 7,
    "name": "John Jingleheimer",
    "email": "billing@lokowebdesign.com",
    "phone": "9876543210",
    "address1": "",
    "address2": "",
    "city": "",
    "state": "",
    "zip": "",
    "guestOf": "",
    "plusOne": "Jane Jingleheimer",
    "children": 0,
    "attending": "Yes",
    "dateTime": "2025-05-14T22:45:37.097Z",
    "createdAt": "2025-05-14T22:50:32.594Z"
  }
]